thumbor_gcs/__init__.py
thumbor_gcs/client.py
thumbor_gcs/config.py
thumbor_gcs/storage_manager.py
thumbor_gcs/loader/__init__.py
thumbor_gcs/loader/gcs_loader.py
thumbor_gcs/result_storage/__init__.py
thumbor_gcs/result_storage/gcs_result_storage.py
thumbor_gcs-0.0.10.dist-info/LICENSE
thumbor_gcs-0.0.10.dist-info/METADATA
thumbor_gcs-0.0.10.dist-info/WHEEL
thumbor_gcs-0.0.10.dist-info/top_level.txt
thumbor_gcs-0.0.10.dist-info/RECORD
