Metadata-Version: 2.1
Name: thumbor-gcs
Version: 0.0.10
Summary: Thumbor Loader and Result Storage for Google Cloud Storage(GCS)
Home-page: https://github.com/jjonline/thumbor-gcs
Author: Jea Yang
Author-email: jjonline@jjonline.cn
Maintainer: Jea Yang
Maintainer-email: jjonline@jjonline.cn
License: Apache-2.0 license
Keywords: thumbor,google cloud platform,google-cloud-storage,imaging,thumbnail,imagemagick
Platform: UNKNOWN
Classifier: Development Status :: 4 - Beta
Classifier: Intended Audience :: Developers
Classifier: Natural Language :: English
Classifier: Operating System :: OS Independent
Classifier: Programming Language :: Python
Classifier: Programming Language :: Python :: 3.9
Classifier: Programming Language :: Python :: 3.10
Classifier: Programming Language :: Python :: 3.11
Classifier: Programming Language :: Python :: 3.12
Classifier: Programming Language :: Python :: Implementation :: CPython
Classifier: Programming Language :: Python :: Implementation :: PyPy
Classifier: Topic :: Software Development :: Libraries :: Python Modules
Requires-Python: >=3.7
License-File: LICENSE
Requires-Dist: thumbor>=7.0.1
Requires-Dist: google-cloud-storage>=2.2.0
